readycloud/__init__.py
readycloud/decorators.py
readycloud/exceptions.py
readycloud/readycloud.py
readycloud/utils.py
readycloud-0.3.2.dist-info/AUTHORS.rst
readycloud-0.3.2.dist-info/LICENSE
readycloud-0.3.2.dist-info/METADATA
readycloud-0.3.2.dist-info/WHEEL
readycloud-0.3.2.dist-info/top_level.txt
readycloud-0.3.2.dist-info/RECORD
