Metadata-Version: 2.1
Name: readycloud
Version: 0.3.2
Summary: Python client for ReadyCloud API.
Home-page: https://github.com/trueship/readycloud-python-client
Author: TrueShip, LLC
Author-email: aljungberg@trueship.com
License: BSD
Keywords: readycloud-python-client
Platform: UNKNOWN
Classifier: Development Status :: 3 - Alpha
Classifier: Intended Audience :: Developers
Classifier: License :: OSI Approved :: BSD License
Classifier: Natural Language :: English
Classifier: Programming Language :: Python :: 2
Classifier: Programming Language :: Python :: 2.6
Classifier: Programming Language :: Python :: 2.7
Classifier: Programming Language :: Python :: 3
Classifier: Programming Language :: Python :: 3.3
Classifier: Programming Language :: Python :: 3.4
Classifier: Programming Language :: Python :: 3.5
Requires-Dist: requests
